AUTHORS.rst
CONTRIBUTING.rst
HISTORY.rst
LICENSE
MANIFEST.in
README.rst
setup.cfg
setup.py
awscli_bastion/__init__.py
awscli_bastion/cache.py
awscli_bastion/cli.py
awscli_bastion/credentials.py
awscli_bastion/minimal.py
awscli_bastion/rotate.py
awscli_bastion/sts.py
awscli_bastion.egg-info/PKG-INFO
awscli_bastion.egg-info/SOURCES.txt
awscli_bastion.egg-info/dependency_links.txt
awscli_bastion.egg-info/entry_points.txt
awscli_bastion.egg-info/not-zip-safe
awscli_bastion.egg-info/requires.txt
awscli_bastion.egg-info/top_level.txt
docs/Makefile
docs/authors.rst
docs/awscli-bastion.png
docs/awscli_bastion.rst
docs/conf.py
docs/contributing.rst
docs/history.rst
docs/index.rst
docs/installation.rst
docs/make.bat
docs/modules.rst
docs/readme.rst
docs/usage.rst
docs/_build/html/_static/ajax-loader.gif
docs/_build/html/_static/comment-bright.png
docs/_build/html/_static/comment-close.png
docs/_build/html/_static/comment.png
docs/_build/html/_static/down-pressed.png
docs/_build/html/_static/down.png
docs/_build/html/_static/file.png
docs/_build/html/_static/minus.png
docs/_build/html/_static/plus.png
docs/_build/html/_static/up-pressed.png
docs/_build/html/_static/up.png
tests/__init__.py
tests/test_awscli_bastion.py