Metadata-Version: 1.2
Name: awscli-bastion
Version: 0.8.3
Summary: awscli-bastion extends the awscli by managing mfa protected short-lived credentials for an aws bastion account.
Home-page: https://github.com/aidanmelen/awscli_bastion
Author: Aidan Melen
Author-email: aidan.l.melen@gmail.com
License: MIT license
Keywords: awscli_bastion
Platform: UNKNOWN
Classifier: Development Status :: 2 - Pre-Alpha
Classifier: Intended Audience :: Developers
Classifier: License :: OSI Approved :: MIT License
Classifier: Natural Language :: English
Classifier: Programming Language :: Python :: 3
Classifier: Programming Language :: Python :: 3.5
Classifier: Programming Language :: Python :: 3.6
Classifier: Programming Language :: Python :: 3.7
Requires-Python: >=3.5
